pixelyodi/__init__.py
pixelyodi/main.py
pixelyodizz-0.3.0.dist-info/METADATA
pixelyodizz-0.3.0.dist-info/WHEEL
pixelyodizz-0.3.0.dist-info/top_level.txt
pixelyodizz-0.3.0.dist-info/RECORD
