Metadata-Version: 2.1
Name: pixelyodizz
Version: 0.3.0
Requires-Dist: pathlib
Requires-Dist: tensorflow
Requires-Dist: matplotlib
Requires-Dist: numpy
Requires-Dist: seaborn
Requires-Dist: IPython
Requires-Dist: gradio
